{
  "schemaVersion": 1,
  "id": "resourcepackchecker",
  "version": "${mod_version}",
  "name": "Server Resource Pack Checker",
  "description": "Server Resource Pack Checker",
  "authors": [
    "Max Henkel"
  ],
  "contact": {
    "website": "https://modrepo.de"
  },
  "license": "All Rights Reserved",
  "icon": "icon.png",
  "environment": "client",
  "entrypoints": {
    "client": [
      "de.maxhenkel.resourcepackchecker.ResourcePackChecker"
    ]
  },
  "mixins": [
    "resourcepackchecker.mixins.json"
  ],
  "depends": {
    "fabricloader": "${fabric_loader_dependency}",
    "minecraft": [
      "1.21",
      "1.21.1"
    ]
  },
  "breaks": {
    "fabric-api": "${fabric_api_dependency_breaks}"
  }
}
